jupyterlab_widgets/__init__.py
jupyterlab_widgets/_version.py
jupyterlab_widgets-3.0.12.data/data/share/jupyter/labextensions/@jupyter-widgets/jupyterlab-manager/install.json
jupyterlab_widgets-3.0.12.data/data/share/jupyter/labextensions/@jupyter-widgets/jupyterlab-manager/package.json
jupyterlab_widgets-3.0.12.data/data/share/jupyter/labextensions/@jupyter-widgets/jupyterlab-manager/schemas/@jupyter-widgets/jupyterlab-manager/package.json.orig
jupyterlab_widgets-3.0.12.data/data/share/jupyter/labextensions/@jupyter-widgets/jupyterlab-manager/schemas/@jupyter-widgets/jupyterlab-manager/plugin.json
jupyterlab_widgets-3.0.12.data/data/share/jupyter/labextensions/@jupyter-widgets/jupyterlab-manager/static/327.006323e9e53e5822022a.js
jupyterlab_widgets-3.0.12.data/data/share/jupyter/labextensions/@jupyter-widgets/jupyterlab-manager/static/39.bb9791c056a3986b18bd.js
jupyterlab_widgets-3.0.12.data/data/share/jupyter/labextensions/@jupyter-widgets/jupyterlab-manager/static/420.84e57ed9c8b0e9ee6181.js
jupyterlab_widgets-3.0.12.data/data/share/jupyter/labextensions/@jupyter-widgets/jupyterlab-manager/static/439.33696bc45fbd403becbb.js
jupyterlab_widgets-3.0.12.data/data/share/jupyter/labextensions/@jupyter-widgets/jupyterlab-manager/static/439.33696bc45fbd403becbb.js.LICENSE.txt
jupyterlab_widgets-3.0.12.data/data/share/jupyter/labextensions/@jupyter-widgets/jupyterlab-manager/static/446.161b182e7ee4a454558f.js
jupyterlab_widgets-3.0.12.data/data/share/jupyter/labextensions/@jupyter-widgets/jupyterlab-manager/static/586.e16bca0292a23e3f76fa.js
jupyterlab_widgets-3.0.12.data/data/share/jupyter/labextensions/@jupyter-widgets/jupyterlab-manager/static/647.5d2a2c067047c425d6aa.js
jupyterlab_widgets-3.0.12.data/data/share/jupyter/labextensions/@jupyter-widgets/jupyterlab-manager/static/651.fe40a967a60b543cf15c.js
jupyterlab_widgets-3.0.12.data/data/share/jupyter/labextensions/@jupyter-widgets/jupyterlab-manager/static/651.fe40a967a60b543cf15c.js.LICENSE.txt
jupyterlab_widgets-3.0.12.dist-info/LICENSE
jupyterlab_widgets-3.0.12.dist-info/METADATA
jupyterlab_widgets-3.0.12.dist-info/WHEEL
jupyterlab_widgets-3.0.12.dist-info/top_level.txt
jupyterlab_widgets-3.0.12.dist-info/RECORD
